{
  "indexes": [
    {
      "collectionGroup": "bookings",
      "queryScope": "COLLECTION",
      "fields": [
        { "fieldPath": "hotelId", "order": "ASCENDING" },
        { "fieldPath": "scheduledStart", "order": "DESCENDING" }
      ]
    },
    {
      "collectionGroup": "bookings",
      "queryScope": "COLLECTION",
      "fields": [
        { "fieldPath": "parentId", "order": "ASCENDING" },
        { "fieldPath": "scheduledStart", "order": "DESCENDING" }
      ]
    },
    {
      "collectionGroup": "bookings",
      "queryScope": "COLLECTION",
      "fields": [
        { "fieldPath": "sitterId", "order": "ASCENDING" },
        { "fieldPath": "status", "order": "ASCENDING" },
        { "fieldPath": "completedAt", "order": "DESCENDING" }
      ]
    },
    {
      "collectionGroup": "sessions",
      "queryScope": "COLLECTION",
      "fields": [
        { "fieldPath": "hotelId", "order": "ASCENDING" },
        { "fieldPath": "status", "order": "ASCENDING" }
      ]
    },
    {
      "collectionGroup": "activityLogs",
      "queryScope": "COLLECTION",
      "fields": [
        { "fieldPath": "sessionId", "order": "ASCENDING" },
        { "fieldPath": "timestamp", "order": "DESCENDING" }
      ]
    },
    {
      "collectionGroup": "notifications",
      "queryScope": "COLLECTION",
      "fields": [
        { "fieldPath": "userId", "order": "ASCENDING" },
        { "fieldPath": "createdAt", "order": "DESCENDING" }
      ]
    },
    {
      "collectionGroup": "notifications",
      "queryScope": "COLLECTION",
      "fields": [
        { "fieldPath": "userId", "order": "ASCENDING" },
        { "fieldPath": "read", "order": "ASCENDING" }
      ]
    },
    {
      "collectionGroup": "incidents",
      "queryScope": "COLLECTION",
      "fields": [
        { "fieldPath": "hotelId", "order": "ASCENDING" },
        { "fieldPath": "createdAt", "order": "DESCENDING" }
      ]
    },
    {
      "collectionGroup": "bookings",
      "queryScope": "COLLECTION",
      "fields": [
        { "fieldPath": "hotelId", "order": "ASCENDING" },
        { "fieldPath": "schedule.date", "order": "ASCENDING" }
      ]
    },
    {
      "collectionGroup": "notifications",
      "queryScope": "COLLECTION",
      "fields": [
        { "fieldPath": "read", "order": "ASCENDING" },
        { "fieldPath": "createdAt", "order": "ASCENDING" }
      ]
    }
  ],
  "fieldOverrides": []
}
